ipx/__init__.py
ipx/arrow.py
ipx/lnc/__init__.py
ipx/lnc/center.py
ipx/lnc/notification.py
ipx/lnc/observer.py
ipx/mem/__init__.py
ipx/mem/cycle.py
ipx/mem/giant.py
ipx/mem/memory.py
ipx/mem/queue.py
ipx/shm/__init__.py
ipx/shm/mmap.py
ipx/shm/mp.py
ipx/shm/shared.py
ipx-0.2.2.dist-info/METADATA
ipx-0.2.2.dist-info/WHEEL
ipx-0.2.2.dist-info/top_level.txt
ipx-0.2.2.dist-info/RECORD
